hmip/__init__.py
hmip/hopfield.py
hmip/other_solvers.py
hmip/utils.py
hmip-0.0.6.dist-info/LICENSE
hmip-0.0.6.dist-info/METADATA
hmip-0.0.6.dist-info/WHEEL
hmip-0.0.6.dist-info/top_level.txt
hmip-0.0.6.dist-info/RECORD
