Metadata-Version: 2.1
Name: hmip
Version: 0.0.6
Summary: Solver for large scale nonlinear mixed integer problems.
Home-page: https://github.com/mathildebadoual/hmip
Author: Mathilde Badoual
Author-email: mathilde.badoual@berkeley.edu
License: UNKNOWN
Platform: UNKNOWN
Classifier: Programming Language :: Python :: 3
Classifier: License :: OSI Approved :: MIT License
Classifier: Operating System :: OS Independent
